odoo/addons/product_barcode_constraint_per_company/README.rst
odoo/addons/product_barcode_constraint_per_company/__init__.py
odoo/addons/product_barcode_constraint_per_company/__manifest__.py
odoo/addons/product_barcode_constraint_per_company/i18n/fr.po
odoo/addons/product_barcode_constraint_per_company/i18n/product_barcode_constraint_per_company.pot
odoo/addons/product_barcode_constraint_per_company/models/__init__.py
odoo/addons/product_barcode_constraint_per_company/models/product_product.py
odoo/addons/product_barcode_constraint_per_company/readme/CONTRIBUTORS.rst
odoo/addons/product_barcode_constraint_per_company/readme/DESCRIPTION.rst
odoo/addons/product_barcode_constraint_per_company/readme/ROADMAP.rst
odoo/addons/product_barcode_constraint_per_company/static/description/icon.png
odoo/addons/product_barcode_constraint_per_company/static/description/index.html
odoo/addons/product_barcode_constraint_per_company/tests/__init__.py
odoo/addons/product_barcode_constraint_per_company/tests/test_module.py
odoo12_addon_product_barcode_constraint_per_company-12.0.1.0.1.dist-info/METADATA
odoo12_addon_product_barcode_constraint_per_company-12.0.1.0.1.dist-info/WHEEL
odoo12_addon_product_barcode_constraint_per_company-12.0.1.0.1.dist-info/top_level.txt
odoo12_addon_product_barcode_constraint_per_company-12.0.1.0.1.dist-info/RECORD
